{
	"name": "LoadAmmexDelta",
	"properties": {
		"activities": [
			{
				"name": "LoopingLkGetSourceObjects",
				"type": "ForEach",
				"dependsOn": [
					{
						"activity": "LkGetSourceObjects",
						"dependencyConditions": [
							"Succeeded"
						]
					}
				],
				"userProperties": [],
				"typeProperties": {
					"items": {
						"value": "@activity('LkGetSourceObjects').output.value",
						"type": "Expression"
					},
					"isSequential": false,
					"batchCount": 3,
					"activities": [
						{
							"name": "ImportingCsvToEdw",
							"type": "Copy",
							"dependsOn": [],
							"policy": {
								"timeout": "7.00:00:00",
								"retry": 0,
								"retryIntervalInSeconds": 30,
								"secureOutput": false,
								"secureInput": false
							},
							"userProperties": [],
							"typeProperties": {
								"source": {
									"type": "DelimitedTextSource",
									"storeSettings": {
										"type": "AzureBlobFSReadSettings",
										"recursive": false,
										"wildcardFolderPath": {
											"value": "@{item().DatalakeIngestRootPath}",
											"type": "Expression"
										},
										"wildcardFileName": "*.*",
										"enablePartitionDiscovery": false
									},
									"formatSettings": {
										"type": "DelimitedTextReadSettings"
									}
								},
								"sink": {
									"type": "SqlDWSink",
									"preCopyScript": {
										"value": "@{item().SinkPreCopyScript}",
										"type": "Expression"
									},
									"writeBehavior": "Insert",
									"sqlWriterUseTableLock": false,
									"tableOption": "autoCreate",
									"disableMetricsCollection": false
								},
								"enableStaging": false,
								"translator": {
									"type": "TabularTranslator",
									"typeConversion": true,
									"typeConversionSettings": {
										"allowDataTruncation": true,
										"treatBooleanAsNumber": false
									}
								}
							},
							"inputs": [
								{
									"referenceName": "LsAdlAmmexEdwDestinationCsv",
									"type": "DatasetReference",
									"parameters": {
										"DatalakeIngestRoot": {
											"value": "@{item().DatalakeIngestRoot}",
											"type": "Expression"
										},
										"DatalakeIngestRootPath": {
											"value": "@{item().DatalakeIngestRootPath}",
											"type": "Expression"
										},
										"DatalakeIngestRootPathFileName": {
											"value": "@toLower('')",
											"type": "Expression"
										}
									}
								}
							],
							"outputs": [
								{
									"referenceName": "DsAsaAmmexEdw_EdwAdfPipelineWrite",
									"type": "DatasetReference",
									"parameters": {
										"Schema": {
											"value": "@{item().SinkSchema}",
											"type": "Expression"
										},
										"Table": {
											"value": "@{item().SinkTable}",
											"type": "Expression"
										}
									}
								}
							]
						}
					]
				}
			},
			{
				"name": "LkGetSourceObjects",
				"type": "Lookup",
				"dependsOn": [],
				"policy": {
					"timeout": "7.00:00:00",
					"retry": 0,
					"retryIntervalInSeconds": 30,
					"secureOutput": false,
					"secureInput": false
				},
				"userProperties": [],
				"typeProperties": {
					"source": {
						"type": "SqlDWSource",
						"sqlReaderQuery": "SELECT *\nFROM [ETL].[AdfLoadControl]\nWHERE [SourceDatabase] = '[Ammex]'\n\t  AND [IsLoad] = 1\n\t  AND [SourceObjectType] = 'Table'\nUNION\nSELECT *\nFROM [ETL].[AdfLoadControl]\nWHERE [SourceSystem] = 'Ammex'\n\t  AND [SourceDatabase] = '[AMMEX_Staging]'\n\t  AND [IsLoad] = 1\nORDER BY [SourceObject]",
						"queryTimeout": "02:00:00",
						"partitionOption": "None"
					},
					"dataset": {
						"referenceName": "DsAsaAmmexEdw_EdwAdfPipelineReadONly",
						"type": "DatasetReference"
					},
					"firstRowOnly": false
				}
			}
		],
		"folder": {
			"name": "2-Load"
		},
		"annotations": []
	}
}