{
	"name": "DsSourceNetworkPathCsvTest",
	"properties": {
		"linkedServiceName": {
			"referenceName": "LsSourceNetworkRoot",
			"type": "LinkedServiceReference"
		},
		"parameters": {
			"SourceNetworkPath": {
				"type": "string"
			}
		},
		"annotations": [],
		"type": "DelimitedText",
		"typeProperties": {
			"location": {
				"type": "FileServerLocation",
				"folderPath": {
					"value": "@dataset().SourceNetworkPath",
					"type": "Expression"
				}
			},
			"columnDelimiter": ",",
			"escapeChar": "\\",
			"firstRowAsHeader": true,
			"quoteChar": "\""
		},
		"schema": [
			{
				"type": "String"
			},
			{
				"type": "String"
			},
			{
				"type": "String"
			},
			{
				"type": "String"
			},
			{
				"type": "String"
			},
			{
				"type": "String"
			},
			{
				"type": "String"
			},
			{
				"type": "String"
			},
			{
				"type": "String"
			},
			{
				"type": "String"
			},
			{
				"type": "String"
			}
		]
	}
}